setup.py
app/__init__.py
app/models.py
app/CommonClass/DataDictClass.py
app/CommonClass/ValidateClass.py
app/CommonClass/__init__.py
app/controller/__init__.py
app/controller/api.py
app/controller/route.py
app/controller/backend/BackendAPIController.py
app/controller/backend/DashboardController.py
app/controller/backend/IndexController.py
app/controller/backend/LanguagesController.py
app/controller/backend/ProjectsController.py
app/controller/backend/RulesController.py
app/controller/backend/SearchController.py
app/controller/backend/TasksController.py
app/controller/backend/VulsController.py
app/controller/backend/WhiteListsController.py
app/controller/backend/__init__.py
cobrad.egg-info/PKG-INFO
cobrad.egg-info/SOURCES.txt
cobrad.egg-info/dependency_links.txt
cobrad.egg-info/requires.txt
cobrad.egg-info/top_level.txt
engine/__init__.py
engine/static.py
pickup/GitTools.py
pickup/__init__.py
pickup/compress.py
pickup/directory.py
pickup/file.py
pickup/subversion.py
utils/__init__.py
utils/common.py
utils/config.py
utils/decompress.py
utils/log.py