Metadata-Version: 1.1
Name: cobrad
Version: 1.3.1
Summary: Code Security Scan System
Home-page: https://github.com/wufeifei/cobra
Author: Feei
Author-email: wufeifei@wufeifei.com
License: MIT
Keywords: static code scan,code security analyse
Platform: any
Classifier: Development Status :: 4 - Beta
Classifier: Intended Audience :: Information Technology
Classifier: Intended Audience :: Developers
Classifier: Intended Audience :: Science/Research
Classifier: Intended Audience :: System Administrators
Classifier: Topic :: Security
Classifier: Topic :: Software Development :: Testing
Classifier: Topic :: Software Development :: Build Tools
Classifier: Topic :: Internet :: WWW/HTTP :: HTTP Servers
Classifier: Topic :: Utilities
Classifier: License :: OSI Approved :: MIT License
Classifier: Programming Language :: Python :: 2
Classifier: Programming Language :: Python :: 2.6
Classifier: Programming Language :: Python :: 2.7
Classifier: Programming Language :: Python :: 3
Classifier: Programming Language :: Python :: 3.3
Classifier: Programming Language :: Python :: 3.4
Classifier: Programming Language :: Python :: 3.5
